[
  {
    "id": "727865b3-c650-45f2-9e69-f802c43adec5",
    "data": [
      {
        "text": "where is the q.peak blk g4.1 datasheet?",
        "userDefined": false
      }
    ],
    "isTemplate": false,
    "count": 0,
    "updated": 0
  },
  {
    "id": "f4e8bbc4-1a9c-488c-ae2d-5bb5194ee041",
    "data": [
      {
        "text": "where is the ",
        "userDefined": false
      },
      {
        "text": "q.peak blk g4.1",
        "alias": "QPEAKBLKG4_1",
        "meta": "@QPEAKBLKG4_1",
        "userDefined": false
      },
      {
        "text": " ",
        "userDefined": false
      },
      {
        "text": "datasheet",
        "alias": "ProdDepDoc",
        "meta": "@ProdDepDoc",
        "userDefined": false
      },
      {
        "text": "?",
        "userDefined": false
      }
    ],
    "isTemplate": false,
    "count": 0,
    "updated": 0
  },
  {
    "id": "5833f2b6-a782-4b53-b1cf-27c3fcb1a8ac",
    "data": [
      {
        "text": "wai",
        "alias": "User",
        "meta": "@User",
        "userDefined": false
      },
      {
        "text": " here. Need you help getting the ",
        "userDefined": false
      },
      {
        "text": "q.peak blk g4.1",
        "alias": "QPEAKBLKG4_1",
        "meta": "@QPEAKBLKG4_1",
        "userDefined": true
      },
      {
        "text": " ",
        "userDefined": false
      },
      {
        "text": "tuv certificate",
        "alias": "ProdIndepDoc",
        "meta": "@ProdIndepDoc",
        "userDefined": false
      }
    ],
    "isTemplate": false,
    "count": 1,
    "updated": 1501980774
  },
  {
    "id": "2bdaeb74-c25b-446c-ad51-4c5693e8b30a",
    "data": [
      {
        "text": "Wai",
        "alias": "User",
        "meta": "@User",
        "userDefined": false
      },
      {
        "text": " her. Can you get me the ",
        "userDefined": false
      },
      {
        "text": "q.peak blk g4.1",
        "alias": "QPEAKBLKG4_1",
        "meta": "@QPEAKBLKG4_1",
        "userDefined": true
      },
      {
        "text": " ",
        "userDefined": false
      },
      {
        "text": "ul certificate",
        "alias": "ProdIndepDoc",
        "meta": "@ProdIndepDoc",
        "userDefined": false
      },
      {
        "text": "?",
        "userDefined": false
      }
    ],
    "isTemplate": false,
    "count": 0,
    "updated": 1501960469
  },
  {
    "id": "c5aa052b-973e-4e65-8b0b-45479b8556d3",
    "data": [
      {
        "text": "Wai",
        "alias": "User",
        "meta": "@User",
        "userDefined": false
      },
      {
        "text": " here. Can you get me the ",
        "userDefined": false
      },
      {
        "text": "q.peak blk g4.1",
        "alias": "QPEAKBLKG4_1",
        "meta": "@QPEAKBLKG4_1",
        "userDefined": true
      },
      {
        "text": " ",
        "userDefined": false
      },
      {
        "text": "warranty",
        "alias": "ProdDepDoc",
        "meta": "@ProdDepDoc",
        "userDefined": false
      },
      {
        "text": " document?",
        "userDefined": false
      }
    ],
    "isTemplate": false,
    "count": 0,
    "updated": 1501960469
  },
  {
    "id": "a544201e-7df8-44e0-b903-77b38da13dc3",
    "data": [
      {
        "text": "q.peak blk g4.1",
        "alias": "QPEAKBLKG4_1",
        "meta": "@QPEAKBLKG4_1",
        "userDefined": true
      },
      {
        "text": " ",
        "userDefined": false
      },
      {
        "text": "warranty",
        "alias": "ProdDepDoc",
        "meta": "@ProdDepDoc",
        "userDefined": false
      },
      {
        "text": " please",
        "userDefined": false
      }
    ],
    "isTemplate": false,
    "count": 0,
    "updated": 1501960469
  },
  {
    "id": "8596d994-e42e-49ef-a49e-d5e272aeec56",
    "data": [
      {
        "text": "wai",
        "alias": "User",
        "meta": "@User",
        "userDefined": false
      },
      {
        "text": " here. need your help getting the ",
        "userDefined": false
      },
      {
        "text": "q.peak blk g4.1",
        "alias": "QPEAKBLKG4_1",
        "meta": "@QPEAKBLKG4_1",
        "userDefined": true
      },
      {
        "text": " ",
        "userDefined": false
      },
      {
        "text": "datasheet",
        "alias": "ProdDepDoc",
        "meta": "@ProdDepDoc",
        "userDefined": false
      }
    ],
    "isTemplate": false,
    "count": 0,
    "updated": 1501960469
  },
  {
    "id": "cd1c63a7-7fbd-4ac0-a741-a0838b8334ec",
    "data": [
      {
        "text": "wai",
        "alias": "User",
        "meta": "@User",
        "userDefined": false
      },
      {
        "text": " here. can you help me getting a ",
        "userDefined": false
      },
      {
        "text": "q.peak blk g4.1",
        "alias": "QPEAKBLKG4_1",
        "meta": "@QPEAKBLKG4_1",
        "userDefined": true
      },
      {
        "text": " ",
        "userDefined": false
      },
      {
        "text": "datasheet",
        "alias": "ProdDepDoc",
        "meta": "@ProdDepDoc",
        "userDefined": false
      },
      {
        "text": "?",
        "userDefined": false
      }
    ],
    "isTemplate": false,
    "count": 0,
    "updated": 1501960469
  },
  {
    "id": "e12ea52e-59a0-4fe9-a4d4-8ae7fbdc479b",
    "data": [
      {
        "text": "wai",
        "alias": "User",
        "meta": "@User",
        "userDefined": false
      },
      {
        "text": " here. would really appreciate if you can help getting the ",
        "userDefined": false
      },
      {
        "text": "q.peak blk g4.1",
        "alias": "QPEAKBLKG4_1",
        "meta": "@QPEAKBLKG4_1",
        "userDefined": true
      },
      {
        "text": " ",
        "userDefined": false
      },
      {
        "text": "datasheet",
        "alias": "ProdDepDoc",
        "meta": "@ProdDepDoc",
        "userDefined": false
      }
    ],
    "isTemplate": false,
    "count": 0,
    "updated": 1501960469
  },
  {
    "id": "4757ee17-f8bb-4892-b44e-d73c49f503d8",
    "data": [
      {
        "text": "wilma",
        "alias": "given-name",
        "meta": "@sys.given-name",
        "userDefined": false
      },
      {
        "text": ", can you please get me the ",
        "userDefined": false
      },
      {
        "text": "q.peak blk g4.1",
        "alias": "QPEAKBLKG4_1",
        "meta": "@QPEAKBLKG4_1",
        "userDefined": true
      },
      {
        "text": " ",
        "userDefined": false
      },
      {
        "text": "datasheet",
        "alias": "ProdDepDoc",
        "meta": "@ProdDepDoc",
        "userDefined": false
      },
      {
        "text": "?",
        "userDefined": false
      }
    ],
    "isTemplate": false,
    "count": 0,
    "updated": 1501960469
  },
  {
    "id": "ddca0768-f302-4471-80d2-a86f815ac677",
    "data": [
      {
        "text": "Q.PEAK BLK G4.1",
        "alias": "QPEAKBLKG4_1",
        "meta": "@QPEAKBLKG4_1",
        "userDefined": true
      },
      {
        "text": " 290",
        "userDefined": false
      }
    ],
    "isTemplate": false,
    "count": 0,
    "updated": 1501907884
  },
  {
    "id": "1e67953a-8e41-4f23-ade9-d02aeaf0d53e",
    "data": [
      {
        "text": "probably g4.1",
        "userDefined": false
      }
    ],
    "isTemplate": false,
    "count": 0,
    "updated": 1501907884
  },
  {
    "id": "a52e0cc8-a9cd-4355-9b6f-1b1e3482615f",
    "data": [
      {
        "text": " ",
        "userDefined": false
      },
      {
        "text": "q.peakblkg4.1",
        "alias": "QPEAKBLKG4_1",
        "meta": "@QPEAKBLKG4_1",
        "userDefined": true
      },
      {
        "text": " ",
        "userDefined": false
      },
      {
        "text": "datasheet",
        "alias": "ProdDepDoc",
        "meta": "@ProdDepDoc",
        "userDefined": false
      },
      {
        "text": " please",
        "userDefined": false
      }
    ],
    "isTemplate": false,
    "count": 0,
    "updated": 0
  },
  {
    "id": "220a022b-4dbd-4b51-b704-a085a79ac2a8",
    "data": [
      {
        "text": "Give me the ",
        "userDefined": false
      },
      {
        "text": "q.peakblkg4.1",
        "alias": "QPEAKBLKG4_1",
        "meta": "@QPEAKBLKG4_1",
        "userDefined": true
      },
      {
        "text": " ",
        "userDefined": false
      },
      {
        "text": "CSA certificate",
        "alias": "ProdIndepDoc",
        "meta": "@ProdIndepDoc",
        "userDefined": false
      }
    ],
    "isTemplate": false,
    "count": 0,
    "updated": 0
  },
  {
    "id": "26a40cf6-a841-48b6-b0b3-fc331e62403b",
    "data": [
      {
        "text": "I need the ",
        "userDefined": false
      },
      {
        "text": "q.peakblkg4.1",
        "alias": "QPEAKBLKG4_1",
        "meta": "@QPEAKBLKG4_1",
        "userDefined": true
      },
      {
        "text": " ",
        "userDefined": false
      },
      {
        "text": "datasheet",
        "alias": "ProdDepDoc",
        "meta": "@ProdDepDoc",
        "userDefined": false
      }
    ],
    "isTemplate": false,
    "count": 0,
    "updated": 0
  },
  {
    "id": "757b1f2c-4f96-47aa-bfa4-2fa115aa61b7",
    "data": [
      {
        "text": "qpeakblkg4.1",
        "alias": "QPEAKBLKG4_1",
        "meta": "@QPEAKBLKG4_1",
        "userDefined": true
      }
    ],
    "isTemplate": false,
    "count": 0,
    "updated": 0
  },
  {
    "id": "1c91e823-2565-4b96-97bf-4d13d1e8f640",
    "data": [
      {
        "text": "qpeakblk-g4.1",
        "alias": "QPEAKBLKG4_1",
        "meta": "@QPEAKBLKG4_1",
        "userDefined": true
      }
    ],
    "isTemplate": false,
    "count": 0,
    "updated": 0
  },
  {
    "id": "aaca2772-42b6-409c-bb43-d85254b36f69",
    "data": [
      {
        "text": "qpeakblk g4.1",
        "alias": "QPEAKBLKG4_1",
        "meta": "@QPEAKBLKG4_1",
        "userDefined": true
      }
    ],
    "isTemplate": false,
    "count": 0,
    "updated": 0
  },
  {
    "id": "9a92c8e1-43a3-442f-ade4-d76f6612a9b5",
    "data": [
      {
        "text": "qpeak blkg4.1",
        "alias": "QPEAKBLKG4_1",
        "meta": "@QPEAKBLKG4_1",
        "userDefined": true
      }
    ],
    "isTemplate": false,
    "count": 0,
    "updated": 0
  },
  {
    "id": "9f8cb29f-d888-4451-8772-36b161696c25",
    "data": [
      {
        "text": "qpeak blk-g4.1",
        "alias": "QPEAKBLKG4_1",
        "meta": "@QPEAKBLKG4_1",
        "userDefined": true
      }
    ],
    "isTemplate": false,
    "count": 0,
    "updated": 0
  },
  {
    "id": "705ff543-03dc-40d2-90c4-b8a893e43c5a",
    "data": [
      {
        "text": "qpeak blk g4.1",
        "alias": "QPEAKBLKG4_1",
        "meta": "@QPEAKBLKG4_1",
        "userDefined": true
      }
    ],
    "isTemplate": false,
    "count": 0,
    "updated": 0
  },
  {
    "id": "ed8003c1-7db1-4ee2-96c3-80e87da15e5d",
    "data": [
      {
        "text": "q.peakblk-g4.1",
        "alias": "QPEAKBLKG4_1",
        "meta": "@QPEAKBLKG4_1",
        "userDefined": true
      }
    ],
    "isTemplate": false,
    "count": 0,
    "updated": 0
  },
  {
    "id": "b47deff6-e410-4201-922b-5b2b884eec4a",
    "data": [
      {
        "text": "q.peak blk-g4.1",
        "alias": "QPEAKBLKG4_1",
        "meta": "@QPEAKBLKG4_1",
        "userDefined": true
      }
    ],
    "isTemplate": false,
    "count": 0,
    "updated": 0
  },
  {
    "id": "fb6bc597-2fb2-4283-9980-7e5f5ca96720",
    "data": [
      {
        "text": "q.peakblkg4.1",
        "alias": "QPEAKBLKG4_1",
        "meta": "@QPEAKBLKG4_1",
        "userDefined": true
      }
    ],
    "isTemplate": false,
    "count": 0,
    "updated": 0
  },
  {
    "id": "17fdb4d9-a6ff-4508-a69b-3cfbd083d250",
    "data": [
      {
        "text": "q.peakblk g4.1",
        "alias": "QPEAKBLKG4_1",
        "meta": "@QPEAKBLKG4_1",
        "userDefined": true
      }
    ],
    "isTemplate": false,
    "count": 0,
    "updated": 0
  },
  {
    "id": "0d0bafdc-495c-4b9f-8474-c8d9315aded1",
    "data": [
      {
        "text": "q.peak blkg4.1",
        "alias": "QPEAKBLKG4_1",
        "meta": "@QPEAKBLKG4_1",
        "userDefined": true
      }
    ],
    "isTemplate": false,
    "count": 0,
    "updated": 0
  },
  {
    "id": "6324d95f-99bc-4798-a6dc-2dd2131e48a5",
    "data": [
      {
        "text": "it is q.peak g4.1",
        "alias": "QPEAKBLKG4_1",
        "meta": "@QPEAKBLKG4_1",
        "userDefined": true
      }
    ],
    "isTemplate": false,
    "count": 0,
    "updated": 0
  },
  {
    "id": "b9af9779-9e09-4b81-9851-f0e150513651",
    "data": [
      {
        "text": "q.peak blk g4.1",
        "alias": "QPEAKBLKG4_1",
        "meta": "@QPEAKBLKG4_1",
        "userDefined": true
      }
    ],
    "isTemplate": false,
    "count": 0,
    "updated": 0
  },
  {
    "id": "78bee014-ac04-44dd-9281-0f170ee8ac89",
    "data": [
      {
        "text": "it is @",
        "userDefined": false
      },
      {
        "text": "QPEAKBLKG4_1",
        "alias": "QPEAKBLKG4_1",
        "meta": "@QPEAKBLKG4_1",
        "userDefined": true
      }
    ],
    "isTemplate": false,
    "count": 0,
    "updated": 0
  },
  {
    "id": "c14aa94a-557f-4744-a3de-2edbcf75c71b",
    "data": [
      {
        "text": "@",
        "userDefined": false
      },
      {
        "text": "QPEAKBLKG4_1",
        "alias": "QPEAKBLKG4_1",
        "meta": "@QPEAKBLKG4_1",
        "userDefined": true
      }
    ],
    "isTemplate": false,
    "count": 0,
    "updated": 0
  }
]