[
  {
    "id": "595b525f-1574-434f-8804-7a1d87fd5a81",
    "data": [
      {
        "text": "Thanks for your help",
        "userDefined": false
      }
    ],
    "isTemplate": false,
    "count": 0,
    "updated": 1500777367
  },
  {
    "id": "a43b2d88-01ca-4dae-aea7-868e189bf4cc",
    "data": [
      {
        "text": "Good job",
        "userDefined": false
      }
    ],
    "isTemplate": false,
    "count": 0,
    "updated": 1500777367
  },
  {
    "id": "e2c5108c-2d20-4ad2-a94a-e36ca2684ae5",
    "data": [
      {
        "text": "Bye",
        "userDefined": false
      }
    ],
    "isTemplate": false,
    "count": 0,
    "updated": 1500777367
  },
  {
    "id": "914aaf45-c5e2-4b9a-978f-71c7c0a20fb8",
    "data": [
      {
        "text": "Thanks",
        "userDefined": false
      }
    ],
    "isTemplate": false,
    "count": 0,
    "updated": 1500777367
  },
  {
    "id": "6b5a88f3-6c56-4c7e-bfd9-aefca80fb7a4",
    "data": [
      {
        "text": "Talk to you again",
        "userDefined": false
      }
    ],
    "isTemplate": false,
    "count": 0,
    "updated": 1500777367
  },
  {
    "id": "bd509602-3037-4493-89ab-24468bd98c04",
    "data": [
      {
        "text": "Talk to you later",
        "userDefined": false
      }
    ],
    "isTemplate": false,
    "count": 0,
    "updated": 1500777367
  },
  {
    "id": "3a997a7f-450f-4c51-8da9-10e7eeb7711e",
    "data": [
      {
        "text": "Have a nice day",
        "userDefined": false
      }
    ],
    "isTemplate": false,
    "count": 0,
    "updated": 1500777367
  }
]