[
  {
    "id": "0547d7e8-85f0-42dd-86b9-60673ab82bd2",
    "data": [
      {
        "text": "Thanks for your help",
        "userDefined": false
      }
    ],
    "isTemplate": false,
    "count": 0,
    "updated": 1500778662
  },
  {
    "id": "387a7c8c-e394-4c82-814a-fccbd7b4f342",
    "data": [
      {
        "text": "Good job",
        "userDefined": false
      }
    ],
    "isTemplate": false,
    "count": 0,
    "updated": 1500778662
  },
  {
    "id": "80227431-8c4d-49cd-87e2-aa2724936a84",
    "data": [
      {
        "text": "Bye",
        "userDefined": false
      }
    ],
    "isTemplate": false,
    "count": 0,
    "updated": 1500778662
  },
  {
    "id": "efaa5ac3-ed8e-4181-b6bd-b4cc014f1076",
    "data": [
      {
        "text": "Thanks",
        "userDefined": false
      }
    ],
    "isTemplate": false,
    "count": 0,
    "updated": 1500778662
  },
  {
    "id": "3aeba5f2-d8f3-4ea8-98b5-40b6cd8944cb",
    "data": [
      {
        "text": "Talk to you again",
        "userDefined": false
      }
    ],
    "isTemplate": false,
    "count": 0,
    "updated": 1500778662
  },
  {
    "id": "43cc4d0c-6c88-4f6a-93f7-5833650f4067",
    "data": [
      {
        "text": "Talk to you later",
        "userDefined": false
      }
    ],
    "isTemplate": false,
    "count": 0,
    "updated": 1500778662
  },
  {
    "id": "8bb823cb-fb48-4cc1-b095-fc1708f29ff7",
    "data": [
      {
        "text": "Have a nice day",
        "userDefined": false
      }
    ],
    "isTemplate": false,
    "count": 0,
    "updated": 1500778662
  }
]