[
  {
    "id": "24e5d3d1-c771-4fe2-a987-36b763096dcd",
    "data": [
      {
        "text": "That\u0027s it for the day.",
        "userDefined": false
      }
    ],
    "isTemplate": false,
    "count": 0,
    "updated": 0
  },
  {
    "id": "0e4d66af-2bd4-4dae-bbc7-c015fdb060fc",
    "data": [
      {
        "text": "No, that\u0027s all I need.",
        "userDefined": false
      }
    ],
    "isTemplate": false,
    "count": 0,
    "updated": 0
  },
  {
    "id": "fef9f5a0-d692-4155-9e08-c0386c994a27",
    "data": [
      {
        "text": "No, thanks.",
        "userDefined": false
      }
    ],
    "isTemplate": false,
    "count": 0,
    "updated": 0
  },
  {
    "id": "27df44fa-b94d-4d31-8425-9bb5dccbb25b",
    "data": [
      {
        "text": "That\u0027s all.",
        "userDefined": false
      }
    ],
    "isTemplate": false,
    "count": 0,
    "updated": 0
  },
  {
    "id": "b851d08f-1272-4f2c-b3aa-a75b44c1601b",
    "data": [
      {
        "text": "That\u0027s all I need",
        "userDefined": false
      }
    ],
    "isTemplate": false,
    "count": 0,
    "updated": 0
  },
  {
    "id": "a8b4a383-c27f-46f2-9014-349611c2c1ea",
    "data": [
      {
        "text": "That\u0027s it",
        "userDefined": false
      }
    ],
    "isTemplate": false,
    "count": 0,
    "updated": 0
  },
  {
    "id": "ca6373c7-2f8c-4ca6-8576-74dfe9214129",
    "data": [
      {
        "text": "No, that\u0027s it.",
        "userDefined": false
      }
    ],
    "isTemplate": false,
    "count": 0,
    "updated": 0
  },
  {
    "id": "dc1316ba-21cf-4903-ac03-23962775d98a",
    "data": [
      {
        "text": "NOT REALLY",
        "userDefined": false
      }
    ],
    "isTemplate": false,
    "count": 0,
    "updated": 0
  },
  {
    "id": "e59874a2-defc-4ed2-bac5-0c5e1f4a9ff3",
    "data": [
      {
        "text": "NO",
        "userDefined": false
      }
    ],
    "isTemplate": false,
    "count": 0,
    "updated": 0
  }
]