[
  {
    "id": "5df34824-cced-45c7-acf6-a684dc854f67",
    "data": [
      {
        "text": "What are the product types again?",
        "userDefined": false
      }
    ],
    "isTemplate": false,
    "count": 0,
    "updated": 1501085439
  },
  {
    "id": "914493cc-028b-497c-b9c3-72f08f8cff6c",
    "data": [
      {
        "text": "What are available again?",
        "userDefined": false
      }
    ],
    "isTemplate": false,
    "count": 0,
    "updated": 1501085439
  },
  {
    "id": "2ea9a4ff-f26b-41d4-9788-9c9d1f5ff07b",
    "data": [
      {
        "text": "What are the options again?",
        "userDefined": false
      }
    ],
    "isTemplate": false,
    "count": 0,
    "updated": 1501085439
  },
  {
    "id": "872da268-ffb1-4b9e-9917-42be28834950",
    "data": [
      {
        "text": "Show me the list again",
        "userDefined": false
      }
    ],
    "isTemplate": false,
    "count": 0,
    "updated": 1501085439
  },
  {
    "id": "855404e9-768c-41f0-8e2b-0e76dbc8f68d",
    "data": [
      {
        "text": "Go back",
        "userDefined": false
      }
    ],
    "isTemplate": false,
    "count": 0,
    "updated": 1500786503
  },
  {
    "id": "59883597-3460-4112-986c-143ae0b8a672",
    "data": [
      {
        "text": "Please go back",
        "userDefined": false
      }
    ],
    "isTemplate": false,
    "count": 0,
    "updated": 1500786503
  },
  {
    "id": "c44d58b7-9319-4e7a-9651-e95c584141d5",
    "data": [
      {
        "text": "Wait, go back",
        "userDefined": false
      }
    ],
    "isTemplate": false,
    "count": 0,
    "updated": 1500786503
  },
  {
    "id": "1a057f2e-5231-4029-80e8-2f72eb4b3984",
    "data": [
      {
        "text": "Come on, go back",
        "userDefined": false
      }
    ],
    "isTemplate": false,
    "count": 0,
    "updated": 1500786503
  }
]