[
  {
    "value": "q.power l g5",
    "synonyms": [
      "q.power l g5",
      "q.power l-g5",
      "q.powerl g5",
      "q.powerl-g5",
      "q.powerlg5",
      "qpower l g5",
      "qpower l-g5",
      "qpowerl g5",
      "qpowerl-g5",
      "qpowerlg5"
    ]
  },
  {
    "value": "q.power lg5",
    "synonyms": [
      "q.power lg5"
    ]
  },
  {
    "value": "q.prower l g5",
    "synonyms": [
      "q.prower l g5"
    ]
  },
  {
    "value": "qpower lg5",
    "synonyms": [
      "qpower lg5"
    ]
  },
  {
    "value": "Q.POWER G5",
    "synonyms": [
      "Q.POWER G5"
    ]
  }
]